era_5g_server/__init__.py
era_5g_server/py.typed
era_5g_server/server.py
era_5g_server-0.5.0.dist-info/METADATA
era_5g_server-0.5.0.dist-info/WHEEL
era_5g_server-0.5.0.dist-info/namespace_packages.txt
era_5g_server-0.5.0.dist-info/top_level.txt
era_5g_server-0.5.0.dist-info/RECORD
