Metadata-Version: 2.1
Name: era-5g-server
Version: 0.5.0
Summary: A server for 5G-ERA Network Applications
Author: Michal Kapinus
Author-email: ikapinus@fit.vutbr.cz
License: LGPL
Classifier: Programming Language :: Python :: 3
Classifier: License :: OSI Approved :: GNU Lesser General Public License v3 (LGPLv3)
Classifier: Operating System :: OS Independent
Classifier: Intended Audience :: Developers
Requires-Python: >=3.8
Requires-Dist: era-5g-interface (~=0.10.0)
Requires-Dist: flask (>=3.0.2)
Requires-Dist: python-engineio (>=4.9.0)
Requires-Dist: python-socketio (>=5.11.1)
Requires-Dist: types-ujson (>=5.8.0.1)
Requires-Dist: ujson (>=5.8.0)
